go_http/__init__.py
go_http/account.py
go_http/contacts.py
go_http/exceptions.py
go_http/metrics.py
go_http/optouts.py
go_http/send.py
go_http/tests/__init__.py
go_http/tests/test_account.py
go_http/tests/test_contacts.py
go_http/tests/test_exceptions.py
go_http/tests/test_metrics.py
go_http/tests/test_optouts.py
go_http/tests/test_send.py
go_http/tests/fixtures/__init__.py
go_http/tests/fixtures/account.py
go_http-0.3.2.dist-info/top_level.txt
go_http-0.3.2.dist-info/METADATA
go_http-0.3.2.dist-info/DESCRIPTION.rst
go_http-0.3.2.dist-info/metadata.json
go_http-0.3.2.dist-info/WHEEL
go_http-0.3.2.dist-info/RECORD
